annas_py/__init__.py
annas_py/extractors/__init__.py
annas_py/extractors/download.py
annas_py/extractors/generic.py
annas_py/extractors/recents.py
annas_py/extractors/search.py
annas_py/models/args.py
annas_py/models/data.py
annas_py/utils.py
annas_py-0.1.0.dist-info/LICENSE
annas_py-0.1.0.dist-info/METADATA
annas_py-0.1.0.dist-info/WHEEL
annas_py-0.1.0.dist-info/RECORD
